{
 "all_non_lhc": [
  "950,230",
  "32,410,136",
  "507,909,281"
 ],
 "amnh_count": [
  4,
  4,
  6
 ],
 "amnh_fqdns": [
  [
   "AMNH-ARES (hosted-ce22.opensciencegrid.org)",
   "AMNH-ARES-CE1 (amnh-ares-ce1.svc.opensciencegrid.org)",
   "AMNH-HEL-CE1 (amnh-hel-ce1.svc.opensciencegrid.org)",
   "AMNH-Mendel-CE1 (amnh-mendel-ce1.svc.opensciencegrid.org)"
  ],
  [
   "AMNH-ARES (hosted-ce22.opensciencegrid.org)",
   "AMNH-ARES-CE1 (amnh-ares-ce1.svc.opensciencegrid.org)",
   "AMNH-HEL-CE1 (amnh-hel-ce1.svc.opensciencegrid.org)",
   "AMNH-Mendel-CE1 (amnh-mendel-ce1.svc.opensciencegrid.org)"
  ],
  [
   "AMNH-ARES (hosted-ce22.opensciencegrid.org)",
   "AMNH-ARES-CE1 (amnh-ares-ce1.svc.opensciencegrid.org)",
   "AMNH-HEL (hosted-ce36.opensciencegrid.org)",
   "AMNH-HEL-CE1 (amnh-hel-ce1.svc.opensciencegrid.org)",
   "AMNH-Mendel (hosted-ce39.opensciencegrid.org)",
   "AMNH-Mendel-CE1 (amnh-mendel-ce1.svc.opensciencegrid.org)"
  ]
 ],
 "amnh_usage": [
  "52,676",
  "818,522",
  "6,931,980"
 ],
 "campus_orgs": [
  "26,728",
  "600,753",
  "26,523,445"
 ],
 "cc_star_count": [
  18,
  19,
  24
 ],
 "cc_star_fqdns": [
  [
   "AMNH-ARES (hosted-ce22.opensciencegrid.org)",
   "AMNH-ARES-CE1 (amnh-ares-ce1.svc.opensciencegrid.org)",
   "AMNH-HEL-CE1 (amnh-hel-ce1.svc.opensciencegrid.org)",
   "AMNH-Mendel-CE1 (amnh-mendel-ce1.svc.opensciencegrid.org)",
   "Georgia_Tech_PACE_CE_2 (osg-sched2.pace.gatech.edu)",
   "LEHIGH-HAWK-CE (osg-hawk-ce.cc.lehigh.edu)",
   "LSU-DB-CE1 (lsu-db-ce1.svc.opensciencegrid.org)",
   "LSUHSC-Tigerfish-CE1 (lsuhsc-tf-ce1.svc.opensciencegrid.org)",
   "ND-CAML_gpu (hosted-ce35.opensciencegrid.org)",
   "OSG_US_SIUE_CC (cc-condor.hpc.siue.edu)",
   "SLATE_US_NMSU_DISCOVERY (osg-ce.nmsu.edu)",
   "SU-ITS-CE2 (its-condor-ce2.syr.edu)",
   "SU-ITS-CE3 (its-condor-ce3.syr.edu)",
   "SU-ITS-CE4 (its-condor-ce4.syr.edu)",
   "TCNJ-ELSA (tcnj-elsa-ce1.svc.opensciencegrid.org)",
   "VU-AUGIE-CE1 (vu-augie-ce1.svc.opensciencegrid.org)",
   "WSU-GRID (hosted-ce33.opensciencegrid.org)",
   "WTAMU-HPC (wtamu-hpc-ce1.svc.opensciencegrid.org)"
  ],
  [
   "AMNH-ARES (hosted-ce22.opensciencegrid.org)",
   "AMNH-ARES-CE1 (amnh-ares-ce1.svc.opensciencegrid.org)",
   "AMNH-HEL-CE1 (amnh-hel-ce1.svc.opensciencegrid.org)",
   "AMNH-Mendel-CE1 (amnh-mendel-ce1.svc.opensciencegrid.org)",
   "Georgia_Tech_PACE_CE_2 (osg-sched2.pace.gatech.edu)",
   "LEHIGH-HAWK-CE (osg-hawk-ce.cc.lehigh.edu)",
   "LSU-DB-CE1 (lsu-db-ce1.svc.opensciencegrid.org)",
   "LSUHSC-Tigerfish-CE1 (lsuhsc-tf-ce1.svc.opensciencegrid.org)",
   "ND-CAML_gpu (hosted-ce35.opensciencegrid.org)",
   "OSG_US_SIUE_CC (cc-condor.hpc.siue.edu)",
   "SDSC-TS-CE1 (sdsc-ts-ce1.svc.opensciencegrid.org)",
   "SLATE_US_NMSU_DISCOVERY (osg-ce.nmsu.edu)",
   "SU-ITS-CE2 (its-condor-ce2.syr.edu)",
   "SU-ITS-CE3 (its-condor-ce3.syr.edu)",
   "SU-ITS-CE4 (its-condor-ce4.syr.edu)",
   "TCNJ-ELSA (tcnj-elsa-ce1.svc.opensciencegrid.org)",
   "VU-AUGIE-CE1 (vu-augie-ce1.svc.opensciencegrid.org)",
   "WSU-GRID (hosted-ce33.opensciencegrid.org)",
   "WTAMU-HPC (wtamu-hpc-ce1.svc.opensciencegrid.org)"
  ],
  [
   "AMNH-ARES (hosted-ce22.opensciencegrid.org)",
   "AMNH-ARES-CE1 (amnh-ares-ce1.svc.opensciencegrid.org)",
   "AMNH-HEL (hosted-ce36.opensciencegrid.org)",
   "AMNH-HEL-CE1 (amnh-hel-ce1.svc.opensciencegrid.org)",
   "AMNH-Mendel (hosted-ce39.opensciencegrid.org)",
   "AMNH-Mendel-CE1 (amnh-mendel-ce1.svc.opensciencegrid.org)",
   "Clarkson-ACRES (hosted-ce37.opensciencegrid.org)",
   "Georgia_Tech_PACE_CE_2 (osg-sched2.pace.gatech.edu)",
   "LEHIGH-HAWK-CE (osg-hawk-ce.cc.lehigh.edu)",
   "LSU-DB-CE1 (lsu-db-ce1.svc.opensciencegrid.org)",
   "LSUHSC-Tigerfish-CE1 (lsuhsc-tf-ce1.svc.opensciencegrid.org)",
   "ND-CAML_gpu (hosted-ce35.opensciencegrid.org)",
   "OSG_US_SIUE_CC (cc-condor.hpc.siue.edu)",
   "SDSC-TS-CE1 (sdsc-ts-ce1.svc.opensciencegrid.org)",
   "SLATE_US_NMSU_DISCOVERY (osg-ce.nmsu.edu)",
   "SU-ITS-CE2 (its-condor-ce2.syr.edu)",
   "SU-ITS-CE3 (its-condor-ce3.syr.edu)",
   "SU-ITS-CE4 (its-condor-ce4.syr.edu)",
   "TCNJ-ELSA (tcnj-elsa-ce1.svc.opensciencegrid.org)",
   "TCNJ-ELSA-old (hosted-ce30.opensciencegrid.org)",
   "Tufts-Cluster (tufts-cluster-ce1.svc.opensciencegrid.org)",
   "VU-AUGIE-CE1 (vu-augie-ce1.svc.opensciencegrid.org)",
   "WSU-GRID (hosted-ce33.opensciencegrid.org)",
   "WTAMU-HPC (wtamu-hpc-ce1.svc.opensciencegrid.org)"
  ]
 ],
 "cc_star_gpu_count": [
  6,
  8,
  12
 ],
 "cc_star_gpu_fqdns": [
  [
   "AMNH-HEL-CE1 (amnh-hel-ce1.svc.opensciencegrid.org)",
   "Georgia_Tech_PACE_CE_2 (osg-sched2.pace.gatech.edu)",
   "LSU-DB-CE1 (lsu-db-ce1.svc.opensciencegrid.org)",
   "ND-CAML_gpu (hosted-ce35.opensciencegrid.org)",
   "TCNJ-ELSA (tcnj-elsa-ce1.svc.opensciencegrid.org)",
   "WSU-GRID (hosted-ce33.opensciencegrid.org)"
  ],
  [
   "AMNH-HEL-CE1 (amnh-hel-ce1.svc.opensciencegrid.org)",
   "Georgia_Tech_PACE_CE_2 (osg-sched2.pace.gatech.edu)",
   "LSU-DB-CE1 (lsu-db-ce1.svc.opensciencegrid.org)",
   "ND-CAML_gpu (hosted-ce35.opensciencegrid.org)",
   "SU-ITS-CE2 (its-condor-ce2.syr.edu)",
   "SU-ITS-CE3 (its-condor-ce3.syr.edu)",
   "TCNJ-ELSA (tcnj-elsa-ce1.svc.opensciencegrid.org)",
   "WSU-GRID (hosted-ce33.opensciencegrid.org)"
  ],
  [
   "AMNH-HEL (hosted-ce36.opensciencegrid.org)",
   "AMNH-HEL-CE1 (amnh-hel-ce1.svc.opensciencegrid.org)",
   "AMNH-Mendel (hosted-ce39.opensciencegrid.org)",
   "AMNH-Mendel-CE1 (amnh-mendel-ce1.svc.opensciencegrid.org)",
   "Georgia_Tech_PACE_CE_2 (osg-sched2.pace.gatech.edu)",
   "LSU-DB-CE1 (lsu-db-ce1.svc.opensciencegrid.org)",
   "ND-CAML_gpu (hosted-ce35.opensciencegrid.org)",
   "SU-ITS-CE2 (its-condor-ce2.syr.edu)",
   "SU-ITS-CE3 (its-condor-ce3.syr.edu)",
   "TCNJ-ELSA (tcnj-elsa-ce1.svc.opensciencegrid.org)",
   "Tufts-Cluster (tufts-cluster-ce1.svc.opensciencegrid.org)",
   "WSU-GRID (hosted-ce33.opensciencegrid.org)"
  ]
 ],
 "cc_star_gpu_usage": [
  "3,163",
  "130,262",
  "1,453,972"
 ],
 "cc_star_usage": [
  "532,155",
  "12,582,695",
  "207,887,974"
 ],
 "gpu_usage": [
  "30,940",
  "788,715",
  "12,187,177"
 ],
 "last_update": 1638859713,
 "last_update_str": "2021-12-07 00:48",
 "multi_inst": [
  "444,057",
  "18,476,047",
  "242,794,100"
 ],
 "osg_connect": [
  "479,444",
  "13,333,335",
  "238,591,735"
 ]
}
