{
 "all_non_lhc": [
  "999,015",
  "28,229,327",
  "389,970,908"
 ],
 "amnh_count": [
  1,
  3,
  3
 ],
 "amnh_fqdns": [
  [
   "AMNH-Mendel-CE1 (amnh-mendel-ce1.svc.opensciencegrid.org)"
  ],
  [
   "AMNH-ARES-CE1 (amnh-ares-ce1.svc.opensciencegrid.org)",
   "AMNH-HEL-CE1 (amnh-hel-ce1.svc.opensciencegrid.org)",
   "AMNH-Mendel-CE1 (amnh-mendel-ce1.svc.opensciencegrid.org)"
  ],
  [
   "AMNH-ARES-CE1 (amnh-ares-ce1.svc.opensciencegrid.org)",
   "AMNH-HEL-CE1 (amnh-hel-ce1.svc.opensciencegrid.org)",
   "AMNH-Mendel-CE1 (amnh-mendel-ce1.svc.opensciencegrid.org)"
  ]
 ],
 "amnh_usage": [
  "11,493",
  "688,389",
  "6,728,331"
 ],
 "campus_orgs": [
  "12,861",
  "413,987",
  "16,333,242"
 ],
 "cc_star_count": [
  23,
  27,
  32
 ],
 "cc_star_fqdns": [
  [
   "AMNH-Mendel-CE1 (amnh-mendel-ce1.svc.opensciencegrid.org)",
   "Alabama-CHPC-CE1 (ua-hpc-ce1.svc.opensciencegrid.org)",
   "Clarkson-ACRES-CE2 (clarkson-acres-ce2.svc.opensciencegrid.org)",
   "Georgia_Tech_PACE_CE_2 (osg-sched2.pace.gatech.edu)",
   "LEHIGH-HAWK-CE (osg-hawk-ce.cc.lehigh.edu)",
   "LSU-DB-CE1 (lsu-db-ce1.svc.opensciencegrid.org)",
   "LSUHSC-Tigerfish-CE2 (lsuhsc-tf-ce2.svc.opensciencegrid.org)",
   "Maine-ACG-CE1 (maine-acg-ce1.svc.opensciencegrid.org)",
   "ND-CAML_gpu (hosted-ce35.opensciencegrid.org)",
   "NMSU-Discovery-CE1 (nmsu-discovery-ce1.svc.opensciencegrid.org)",
   "OSG_US_SIUE_CC (cc-condor.hpc.siue.edu)",
   "PDX-Coeus-CE1 (pdx-coeus-ce1.svc.opensciencegrid.org)",
   "Rhodes-HPC-CE1 (rhodes-hpc-ce1.svc.opensciencegrid.org)",
   "SU-ITS-AD-CE4 (its-condor-ce4.ad.syr.edu)",
   "SU-ITS-CE2 (its-condor-ce2.syr.edu)",
   "SU-ITS-CE3 (its-condor-ce3.syr.edu)",
   "TCNJ-ELSA-CE2 (tcnj-elsa-ce2.svc.opensciencegrid.org)",
   "UC-Denver-CE1 (uc-denver-ce1.svc.opensciencegrid.org)",
   "UTC-Epyc (utc-epyc-ce1.svc.opensciencegrid.org)",
   "UW-IT-CE1 (uw-it-ce1.svc.opensciencegrid.org)",
   "VU-AUGIE-CE1 (vu-augie-ce1.svc.opensciencegrid.org)",
   "WSU-GRID-CE1 (wsu-grid-ce1.svc.opensciencegrid.org)",
   "WTAMU-HPC (wtamu-hpc-ce1.svc.opensciencegrid.org)"
  ],
  [
   "AMNH-ARES-CE1 (amnh-ares-ce1.svc.opensciencegrid.org)",
   "AMNH-HEL-CE1 (amnh-hel-ce1.svc.opensciencegrid.org)",
   "AMNH-Mendel-CE1 (amnh-mendel-ce1.svc.opensciencegrid.org)",
   "Alabama-CHPC-CE1 (ua-hpc-ce1.svc.opensciencegrid.org)",
   "Clarkson-ACRES-CE2 (clarkson-acres-ce2.svc.opensciencegrid.org)",
   "FANDM-ITS-CE1 (fandm-its-ce1.svc.opensciencegrid.org)",
   "Georgia_Tech_PACE_CE_2 (osg-sched2.pace.gatech.edu)",
   "LEHIGH-HAWK-CE (osg-hawk-ce.cc.lehigh.edu)",
   "LSU-DB-CE1 (lsu-db-ce1.svc.opensciencegrid.org)",
   "LSUHSC-Tigerfish-CE2 (lsuhsc-tf-ce2.svc.opensciencegrid.org)",
   "Maine-ACG-CE1 (maine-acg-ce1.svc.opensciencegrid.org)",
   "ND-CAML_gpu (hosted-ce35.opensciencegrid.org)",
   "NMSU-Discovery-CE1 (nmsu-discovery-ce1.svc.opensciencegrid.org)",
   "OSG_US_SIUE_CC (cc-condor.hpc.siue.edu)",
   "PDX-Coeus-CE1 (pdx-coeus-ce1.svc.opensciencegrid.org)",
   "Rhodes-HPC-CE1 (rhodes-hpc-ce1.svc.opensciencegrid.org)",
   "SU-ITS-AD-CE4 (its-condor-ce4.ad.syr.edu)",
   "SU-ITS-CE2 (its-condor-ce2.syr.edu)",
   "SU-ITS-CE3 (its-condor-ce3.syr.edu)",
   "TCNJ-ELSA-CE2 (tcnj-elsa-ce2.svc.opensciencegrid.org)",
   "Tufts-Cluster (tufts-cluster-ce1.svc.opensciencegrid.org)",
   "UC-Denver-CE1 (uc-denver-ce1.svc.opensciencegrid.org)",
   "UTC-Epyc (utc-epyc-ce1.svc.opensciencegrid.org)",
   "UW-IT-CE1 (uw-it-ce1.svc.opensciencegrid.org)",
   "VU-AUGIE-CE1 (vu-augie-ce1.svc.opensciencegrid.org)",
   "WSU-GRID-CE1 (wsu-grid-ce1.svc.opensciencegrid.org)",
   "WTAMU-HPC (wtamu-hpc-ce1.svc.opensciencegrid.org)"
  ],
  [
   "AMNH-ARES-CE1 (amnh-ares-ce1.svc.opensciencegrid.org)",
   "AMNH-HEL-CE1 (amnh-hel-ce1.svc.opensciencegrid.org)",
   "AMNH-Mendel-CE1 (amnh-mendel-ce1.svc.opensciencegrid.org)",
   "Alabama-CHPC-CE1 (ua-hpc-ce1.svc.opensciencegrid.org)",
   "Clarkson-ACRES-CE2 (clarkson-acres-ce2.svc.opensciencegrid.org)",
   "FANDM-ITS-CE1 (fandm-its-ce1.svc.opensciencegrid.org)",
   "Georgia_Tech_PACE_CE_2 (osg-sched2.pace.gatech.edu)",
   "LEHIGH-HAWK-CE (osg-hawk-ce.cc.lehigh.edu)",
   "LSU-DB-CE1 (lsu-db-ce1.svc.opensciencegrid.org)",
   "LSUHSC-Tigerfish-CE1 (lsuhsc-tf-ce1.svc.opensciencegrid.org)",
   "LSUHSC-Tigerfish-CE2 (lsuhsc-tf-ce2.svc.opensciencegrid.org)",
   "Maine-ACG-CE1 (maine-acg-ce1.svc.opensciencegrid.org)",
   "ND-CAML_gpu (hosted-ce35.opensciencegrid.org)",
   "NMSU-Discovery-CE1 (nmsu-discovery-ce1.svc.opensciencegrid.org)",
   "OSG_US_SIUE_CC (cc-condor.hpc.siue.edu)",
   "PDX-Coeus-CE1 (pdx-coeus-ce1.svc.opensciencegrid.org)",
   "Rhodes-HPC-CE1 (rhodes-hpc-ce1.svc.opensciencegrid.org)",
   "SLATE_US_NMSU_DISCOVERY (osg-ce.nmsu.edu)",
   "SU-ITS-AD-CE4 (its-condor-ce4.ad.syr.edu)",
   "SU-ITS-CE2 (its-condor-ce2.syr.edu)",
   "SU-ITS-CE3 (its-condor-ce3.syr.edu)",
   "SU-ITS-CE4 (its-condor-ce4.syr.edu)",
   "TCNJ-ELSA (tcnj-elsa-ce1.svc.opensciencegrid.org)",
   "TCNJ-ELSA-CE2 (tcnj-elsa-ce2.svc.opensciencegrid.org)",
   "Tufts-Cluster (tufts-cluster-ce1.svc.opensciencegrid.org)",
   "UC-Denver-CE1 (uc-denver-ce1.svc.opensciencegrid.org)",
   "UTC-Epyc (utc-epyc-ce1.svc.opensciencegrid.org)",
   "UW-IT-CE1 (uw-it-ce1.svc.opensciencegrid.org)",
   "VU-AUGIE-CE1 (vu-augie-ce1.svc.opensciencegrid.org)",
   "WSU-GRID (hosted-ce33.opensciencegrid.org)",
   "WSU-GRID-CE1 (wsu-grid-ce1.svc.opensciencegrid.org)",
   "WTAMU-HPC (wtamu-hpc-ce1.svc.opensciencegrid.org)"
  ]
 ],
 "cc_star_gpu_count": [
  5,
  6,
  12
 ],
 "cc_star_gpu_fqdns": [
  [
   "AMNH-Mendel-CE1 (amnh-mendel-ce1.svc.opensciencegrid.org)",
   "Georgia_Tech_PACE_CE_2 (osg-sched2.pace.gatech.edu)",
   "LSU-DB-CE1 (lsu-db-ce1.svc.opensciencegrid.org)",
   "PDX-Coeus-CE1 (pdx-coeus-ce1.svc.opensciencegrid.org)",
   "WSU-GRID-CE1 (wsu-grid-ce1.svc.opensciencegrid.org)"
  ],
  [
   "AMNH-HEL-CE1 (amnh-hel-ce1.svc.opensciencegrid.org)",
   "AMNH-Mendel-CE1 (amnh-mendel-ce1.svc.opensciencegrid.org)",
   "Georgia_Tech_PACE_CE_2 (osg-sched2.pace.gatech.edu)",
   "LSU-DB-CE1 (lsu-db-ce1.svc.opensciencegrid.org)",
   "PDX-Coeus-CE1 (pdx-coeus-ce1.svc.opensciencegrid.org)",
   "WSU-GRID-CE1 (wsu-grid-ce1.svc.opensciencegrid.org)"
  ],
  [
   "AMNH-HEL-CE1 (amnh-hel-ce1.svc.opensciencegrid.org)",
   "AMNH-Mendel-CE1 (amnh-mendel-ce1.svc.opensciencegrid.org)",
   "Georgia_Tech_PACE_CE_2 (osg-sched2.pace.gatech.edu)",
   "LSU-DB-CE1 (lsu-db-ce1.svc.opensciencegrid.org)",
   "PDX-Coeus-CE1 (pdx-coeus-ce1.svc.opensciencegrid.org)",
   "SU-ITS-CE2 (its-condor-ce2.syr.edu)",
   "SU-ITS-CE3 (its-condor-ce3.syr.edu)",
   "TCNJ-ELSA (tcnj-elsa-ce1.svc.opensciencegrid.org)",
   "Tufts-Cluster (tufts-cluster-ce1.svc.opensciencegrid.org)",
   "UTC-Epyc (utc-epyc-ce1.svc.opensciencegrid.org)",
   "WSU-GRID (hosted-ce33.opensciencegrid.org)",
   "WSU-GRID-CE1 (wsu-grid-ce1.svc.opensciencegrid.org)"
  ]
 ],
 "cc_star_gpu_usage": [
  "889",
  "14,620",
  "218,708"
 ],
 "cc_star_usage": [
  "300,322",
  "18,414,935",
  "252,284,739"
 ],
 "gpu_usage": [
  "27,277",
  "1,094,297",
  "12,395,513"
 ],
 "last_update": 1683528513,
 "last_update_str": "2023-05-08 01:48",
 "multi_inst": [
  "287,105",
  "14,843,189",
  "199,743,084"
 ],
 "osg_connect": [
  "699,048",
  "12,972,149",
  "173,894,581"
 ]
}
